boxxy.py
boxxy-1.2.dist-info/LICENSE.txt
boxxy-1.2.dist-info/WHEEL
boxxy-1.2.dist-info/METADATA
boxxy-1.2.dist-info/RECORD
