Metadata-Version: 2.3
Name: boxxy
Version: 1.2
Summary: Provides utilities for drawing fancy text boxes and tables using the Unicode Box Drawings block.
Author-email: Artemis <artemis.martensson@gmail.com>
Requires-Python: >= 3
Classifier: Development Status :: 4 - Beta
Classifier: Environment :: Console
Classifier: Intended Audience :: Developers
Classifier: License :: OSI Approved :: MIT License
Classifier: Operating System :: OS Independent
Classifier: Programming Language :: Python :: 3
Classifier: Topic :: Utilities
Project-URL: Homepage, https://github.com/farpoke/boxxy
